qt4w/__init__.py
qt4w/util.py
qt4w/webcontrols.py
qt4w/browser/__init__.py
qt4w/browser/browser.py
qt4w/webdriver/__init__.py
qt4w/webdriver/iewebdriver.py
qt4w/webdriver/webdriver.py
qt4w/webdriver/webkitwebdriver.py
qt4w/webview/__init__.py
qt4w/webview/webview.py
qt4w-2.2.0.dist-info/LICENSE.TXT
qt4w-2.2.0.dist-info/METADATA
qt4w-2.2.0.dist-info/WHEEL
qt4w-2.2.0.dist-info/top_level.txt
qt4w-2.2.0.dist-info/RECORD
