Metadata-Version: 2.1
Name: qt4w
Version: 2.2.0
Summary: QTA driver for Web
Home-page: https://github.com/qtacore/QT4W
Author: Tencent
License: Copyright(c)2010-2018 Tencent All Rights Reserved. 
Project-URL: QT4W Documentation, https://qt4w.readthedocs.io/zh_CN/latest/
Classifier: Programming Language :: Python :: 2.7
Classifier: Programming Language :: Python :: 3.5
Classifier: Programming Language :: Python :: 3.6
Classifier: Programming Language :: Python :: 3.7
Classifier: Operating System :: OS Independent
License-File: LICENSE.TXT
Requires-Dist: six
Requires-Dist: tornado ==5.1.1
